[
  {
    "id": "evt-001",
    "title": "洛前出生",
    "type": "birth",
    "article": "演进轨迹/事册之载/11-禪通纪/01-伏羲朝代/15-祝融氏/04-昊天卌九帝洛前祝融氏纪",
    "paragraphs": ["1"],
    "time_text": "昊天上元千五百九十五载",
    "year": 1595,
    "people": ["洛前"],
    "places": ["太白"],
    "summary": "祝融氏有子生于太白，帝洛矛并帝附前之侄，得名洛前"
  },
  {
    "id": "evt-002",
    "title": "洛前继位",
    "type": "reign",
    "article": "演进轨迹/事册之载/11-禪通纪/01-伏羲朝代/15-祝融氏/04-昊天卌九帝洛前祝融氏纪",
    "paragraphs": ["2"],
    "time_text": "昊天上元千六百廿八载于辛未",
    "year": 1628,
    "people": ["洛前", "附前"],
    "places": ["象邑"],
    "summary": "帝附前崩，侄洛前立，居象邑"
  },
  {
    "id": "evt-003",
    "title": "洛前被黜",
    "type": "politics",
    "article": "演进轨迹/事册之载/11-禪通纪/01-伏羲朝代/15-祝融氏/04-昊天卌九帝洛前祝融氏纪",
    "paragraphs": ["3"],
    "time_text": "昊天上元千六百六十载于癸卯",
    "year": 1660,
    "people": ["洛前"],
    "summary": "多酋共请于伏羲氏，黜其政"
  },
  {
    "id": "evt-004",
    "title": "洛前去世",
    "type": "death",
    "article": "演进轨迹/事册之载/11-禪通纪/01-伏羲朝代/15-祝融氏/04-昊天卌九帝洛前祝融氏纪",
    "paragraphs": ["3"],
    "time_text": "昊天上元千六百六十载于癸卯",
    "year": 1660,
    "people": ["洛前"],
    "places": ["帝冢"],
    "summary": "帝闻之忧愤成疾，竟崩，葬帝冢，寿计六十六岁"
  }
]