{
  "events": [
    {
      "id": "evt-shigong-001",
      "title": "施公诞生",
      "type": "birth",
      "article": "演进轨迹/事册之载/11-禪通纪/01-伏羲朝代/11-骊连氏/02-昊天卅一世帝施公骊连氏纪",
      "paragraphs": ["1"],
      "time_text": "昊天上元千又七十一载",
      "year": 1071,
      "people": ["施公", "泰望"],
      "places": ["骊山"],
      "summary": "骊连氏生男于骊山，姓风，帝泰望侄，以其才智而率氏为酋，得名施公"
    },
    {
      "id": "evt-shigong-002",
      "title": "施公立为帝",
      "type": "reign",
      "article": "演进轨迹/事册之载/11-禪通纪/01-伏羲朝代/11-骊连氏/02-昊天卅一世帝施公骊连氏纪",
      "paragraphs": ["2"],
      "time_text": "昊天上元千百又七载于庚寅",
      "year": 1107,
      "people": ["施公", "泰望"],
      "places": ["象邑"],
      "summary": "帝泰望崩，嗣施公立，居象邑"
    },
    {
      "id": "evt-shigong-003",
      "title": "施公崩",
      "type": "death",
      "article": "演进轨迹/事册之载/11-禪通纪/01-伏羲朝代/11-骊连氏/02-昊天卅一世帝施公骊连氏纪",
      "paragraphs": ["3"],
      "time_text": "昊天和元千百四十载于癸亥",
      "year": 1140,
      "people": ["施公"],
      "places": ["象邑"],
      "summary": "帝崩，寿七十岁，葬象邑西南郊，祀名上帝施公"
    }
  ]
}
